README.rst
setup.cfg
setup.py
gocdapi/__init__.py
gocdapi/admin.py
gocdapi/agent.py
gocdapi/agents.py
gocdapi/custom_exceptions.py
gocdapi/go.py
gocdapi/gobase.py
gocdapi/pipeline.py
gocdapi/pipeline_group.py
gocdapi/pipeline_groups.py
gocdapi/stage.py
gocdapi.egg-info/PKG-INFO
gocdapi.egg-info/SOURCES.txt
gocdapi.egg-info/dependency_links.txt
gocdapi.egg-info/entry_points.txt
gocdapi.egg-info/pbr.json
gocdapi.egg-info/requires.txt
gocdapi.egg-info/top_level.txt
gocdapi.egg-info/zip-safe
gocdapi/command_line/__init__.py
gocdapi/command_line/gocdapi_version.py
gocdapi/utils/__init__.py
gocdapi/utils/config_xml.py