Metadata-Version: 1.1
Name: gocdapi
Version: 1.0.3
Summary: A Python API for accessing resources on a Go continuous-delivery server.
Home-page: UNKNOWN
Author: Joao Cravo
Author-email: joaogbcravo@gmail.com
License: MIT
Platform: UNKNOWN
Classifier: Development Status :: 5 - Production/Stable
Classifier: Environment :: Console
Classifier: Environment :: Plugins
Classifier: Intended Audience :: Developers
Classifier: License :: OSI Approved :: MIT License
Classifier: Natural Language :: English
Classifier: Operating System :: OS Independent
Classifier: Programming Language :: Python :: 2.7
Classifier: Topic :: Software Development :: Libraries
